apa102_spi/__init__.py
apa102_spi/apa102_spi.py
apa102_spi-1.0.dist-info/LICENSE
apa102_spi-1.0.dist-info/METADATA
apa102_spi-1.0.dist-info/WHEEL
apa102_spi-1.0.dist-info/top_level.txt
apa102_spi-1.0.dist-info/RECORD
