Metadata-Version: 2.1
Name: apa102-spi
Version: 1.0
Summary: Python library for controlling APA102 LEDs through SPI
Home-page: https://github.com/Frederic98/APA102_SPI
Author: Frederic
License: UNKNOWN
Platform: UNKNOWN
Classifier: Programming Language :: Python :: 3
Classifier: License :: OSI Approved :: MIT License
Classifier: Operating System :: OS Independent
Requires-Python: >=3.6
